{"players":["Anna","Ari","Beata","Beth","Chris","Marina","Vlad"],"draw":{"pools":[["Spain","France","England","Brazil","Portugal","Argentina","Germany"],["Netherlands","Belgium","Norway","Colombia","Morocco","Japan","USA"],["Mexico","Senegal","Switzerland","Turkey","Uruguay","Croatia","Ecuador"],["Sweden","Austria","Canada","Ivory Coast","Algeria","Bosnia & Herzegovina","Czech Republic"],["Egypt","South Korea","Paraguay","Scotland","Australia","Ghana","Iran"],["Tunisia","DR Congo","Cape Verde","Iraq","Jordan","New Zealand","Panama"],["Qatar","Saudi Arabia","South Africa","Uzbekistan","Curaçao","Haiti","Haiti"]],"assignments":{"Spain":[4],"France":[0],"England":[1],"Brazil":[5],"Portugal":[2],"Argentina":[3],"Germany":[6],"Netherlands":[6],"Belgium":[0],"Norway":[2],"Colombia":[3],"Morocco":[4],"Japan":[1],"USA":[5],"Mexico":[4],"Senegal":[5],"Switzerland":[6],"Turkey":[3],"Uruguay":[2],"Croatia":[0],"Ecuador":[1],"Sweden":[1],"Austria":[0],"Canada":[5],"Ivory Coast":[6],"Algeria":[2],"Bosnia & Herzegovina":[4],"Czech Republic":[3],"Egypt":[3],"South Korea":[6],"Paraguay":[5],"Scotland":[1],"Australia":[2],"Ghana":[4],"Iran":[0],"Tunisia":[0],"DR Congo":[6],"Cape Verde":[4],"Iraq":[5],"Jordan":[1],"New Zealand":[2],"Panama":[3],"Qatar":[2],"Saudi Arabia":[0],"South Africa":[1],"Uzbekistan":[4],"Curaçao":[3],"Haiti":[5,6]},"completedAt":1781191018594}}
